Metadata-Version: 2.1
Name: cloudify-utilities-plugins-sdk-without-paramiko
Version: 0.0.49
Summary: Utilities SDK for extending Cloudify
Home-page: https://github.com/cloudify-incubator/cloudify-utilities-plugins-sdk
Author: Cloudify Platform Ltd.
Author-email: hello@cloudify.co
License: Apache License 2.0
Platform: UNKNOWN
Classifier: Programming Language :: Python :: 2.7
Classifier: Programming Language :: Python :: 3
Classifier: License :: OSI Approved :: Apache Software License
Classifier: Operating System :: OS Independent
Requires-Dist: cloudify-common (>=4.5.5)
Requires-Dist: paramiko (>=2.7.1)
Requires-Dist: Jinja2 (>=2.7.2)
Requires-Dist: pycdlib
Requires-Dist: pyyaml (<6.0,>=3.10)
Requires-Dist: requests (<3.0.0,>=2.7.0)
Requires-Dist: xmltodict
Requires-Dist: gitdb (>=0.6.4)
Requires-Dist: GitPython
Requires-Dist: psutil
